MANIFEST.in
README.md
setup.py
bin/gd
bin/td
getdone/Exceptions.py
getdone/GetDone.py
getdone/Task.py
getdone/__init__.py
getdone.egg-info/PKG-INFO
getdone.egg-info/SOURCES.txt
getdone.egg-info/dependency_links.txt
getdone.egg-info/not-zip-safe
getdone.egg-info/requires.txt
getdone.egg-info/top_level.txt