Metadata-Version: 1.1
Name: getdone
Version: 0.1.2
Summary: An integrated ToDo list manager for your commandline
Home-page: https://github.com/durgaswaroop/get-done
Author: Durga Swaroop
Author-email: durgaswaroop@gmail.com
License: MIT
Keywords: todo todolist todo manager getting things done gtd organizer tasks
Platform: UNKNOWN
Classifier: Development Status :: 3 - Alpha
Classifier: License :: OSI Approved :: MIT License
Classifier: Programming Language :: Python :: 3.6
Classifier: Topic :: Utilities
